{
  "stem": "208",
  "timelineKind": "linked-only-scatter",
  "sequenceKind": "single-anchor-delta",
  "eventCount": 1,
  "stemDefaultDurationMs": 120,
  "loopSummary": {
    "startEventIndex": 0,
    "endEventIndex": 0,
    "reason": "linked-scatter",
    "confidence": "low"
  },
  "eventFramePaths": [
    "frames/208/00-g00-linked.png"
  ],
  "events": [
    {
      "groupIndex": 0,
      "eventType": "linked",
      "linkType": "base-frame-delta",
      "anchorFrameIndex": 16,
      "relation": null,
      "tupleCount": 8,
      "chunkIndexRange": [
        2,
        37
      ],
      "durationHintMs": 120,
      "playbackDurationMs": 120,
      "playbackSource": "tail-marker",
      "timingMarkers": [
        "67ff000000",
        "660c000000"
      ],
      "timingValues": [
        255,
        120
      ],
      "timingExplicitValues": [
        120
      ],
      "anchorRecordMarkers": [
        "660c000000"
      ],
      "anchorRecordTimingValues": [
        120
      ],
      "framePath": "frames/208/00-g00-linked.png"
    }
  ]
}